ggp/__init__.py
ggp/make.py
ggp/new.py
ggp/templates/loadworker.js
ggp/templates/sample.html
ggp/templates/sample.js
ggp_template-0.2.0.dist-info/LICENSE
ggp_template-0.2.0.dist-info/METADATA
ggp_template-0.2.0.dist-info/WHEEL
ggp_template-0.2.0.dist-info/top_level.txt
ggp_template-0.2.0.dist-info/RECORD
