Metadata-Version: 2.1
Name: ggp_template
Version: 0.2.0
Summary: Creates and compiles GGP js/html projects
Author-email: Praneeth Kolichala <praneeth.kolichala@gmail.com>
Project-URL: Homepage, https://github.com/prakol16/ggp_template
Project-URL: Bug Tracker, https://github.com/prakol16/ggp_template/issues
Classifier: Programming Language :: Python :: 3
Classifier: License :: OSI Approved :: MIT License
Classifier: Operating System :: OS Independent
Requires-Python: >=3.4
License-File: LICENSE
